MANIFEST.in
README.rst
setup.py
vinda/__init__.py
vinda/template.html
vinda/vinda.py
vinda.egg-info/PKG-INFO
vinda.egg-info/SOURCES.txt
vinda.egg-info/dependency_links.txt
vinda.egg-info/index.html
vinda.egg-info/requires.txt
vinda.egg-info/top_level.txt