Metadata-Version: 1.1
Name: vinda
Version: 0.3.1
Summary: `Help users construct their index pages rapidly
Home-page: https://github.com/luosch/vinda
Author: Sicheng Luo
Author-email: i@lsich.com
License: MIT
Keywords: vinda,index,html
Platform: UNKNOWN
Classifier: License :: OSI Approved :: MIT License
Classifier: Programming Language :: Python
Classifier: Intended Audience :: Developers
Classifier: Operating System :: OS Independent
Classifier: Programming Language :: Python
Classifier: Programming Language :: Python :: 2.7
